evoclearn/plt/__init__.py
evoclearn/plt/_plt.py
evoclearn/plt/version.py
evoclearn_plt-0.1.0.dist-info/LICENSE
evoclearn_plt-0.1.0.dist-info/METADATA
evoclearn_plt-0.1.0.dist-info/WHEEL
evoclearn_plt-0.1.0.dist-info/top_level.txt
evoclearn_plt-0.1.0.dist-info/RECORD
