Metadata-Version: 2.1
Name: evoclearn-plt
Version: 0.1.0
Summary: Plotting tools for Early Vocal Learning simulations.
Home-page: https://gitlab.com/evoc-learn-group/evoc-learn-plt
Author: The EVocLearn Group
Author-email: daniel.r.vanniekerk@gmail.com
License: UNKNOWN
Platform: UNKNOWN
Requires-Python: >=3.7
Requires-Dist: cairosvg (<2.6.0,>=2.5.2)
Requires-Dist: evoclearn-core (<0.19.0,>=0.18.6)
Requires-Dist: matplotlib
Requires-Dist: svgpathtools (<1.6.0,>=1.5.0)
Provides-Extra: dev
Requires-Dist: ipython ; extra == 'dev'
